CHANGELOG.txt
LICENCE
MANIFEST.in
README.txt
setup.py
ashan_utils/__init__.py
ashan_utils.egg-info/PKG-INFO
ashan_utils.egg-info/SOURCES.txt
ashan_utils.egg-info/dependency_links.txt
ashan_utils.egg-info/top_level.txt