Metadata-Version: 2.1
Name: ashan-utils
Version: 0.0.1
Summary: A very basic cumulative value calculator
Home-page: UNKNOWN
Author: Ashan Jaysundara
Author-email: developer.ashan@gmail.com
License: MIT
Keywords: utils
Platform: UNKNOWN
Classifier: Development Status :: 5 - Production/Stable
Classifier: Intended Audience :: Education
Classifier: Operating System :: Microsoft :: Windows :: Windows 10
Classifier: License :: OSI Approved :: MIT License
Classifier: Programming Language :: Python :: 3
License-File: LICENCE
